Workbook

Sheet Cover
B2: Three-Statement Financial Model
B3: Illustrative Manufacturing Co. | 2024A-2025A historical, 2026E-2030E forecast | $ thousands
B5: Purpose | C5: Forecasts the income statement, balance sheet and cash flow statement, fully linked, so a change to any assumption flows through all three.
B6: Data | C6: Illustrative figures for a fictional company. Not real company data.
B7: How to use | C7: Change only the blue cells and yellow cells on the Assumptions sheet. Every other number is a formula.
B8: Scenario | C8: Assumptions!C5 switches the revenue case: 1 = Base, 2 = Upside, 3 = Downside.
B9: Sheets | C9: Assumptions > Income Statement > Balance Sheet > Cash Flow > Checks
B10: Balancing | C10: Cash on the balance sheet comes from the cash flow statement. The Checks sheet confirms assets = liabilities + equity every year.
B11: Colour key | C11: Blue = hardcoded input | Black = formula | Green = link to another sheet | Yellow fill = key assumption to change
B12: Author | C12: Muhammed Anshaj K

Sheet Assumptions
B1: Assumptions
B2: Illustrative Manufacturing Co. ($ thousands)
C4: 2024A | D4: 2025A | E4: 2026E | F4: 2027E | G4: 2028E | H4: 2029E | I4: 2030E
B5: Scenario selector | C5: 1 | D5: =CHOOSE($C$5,"Base","Upside","Downside") -> Base | E5: Type 1 = Base, 2 = Upside, 3 = Downside
B7: Revenue growth
B8: Base case | E8: 0.1 | F8: 0.09 | G8: 0.08 | H8: 0.07 | I8: 0.06
B9: Upside case | E9: 0.14 | F9: 0.12 | G9: 0.11 | H9: 0.1 | I9: 0.09
B10: Downside case | E10: 0.04 | F10: 0.03 | G10: 0.03 | H10: 0.02 | I10: 0.02
B11: Revenue growth used | E11: =CHOOSE($C$5,E8,E9,E10) -> 0.1 | F11: =CHOOSE($C$5,F8,F9,F10) -> 0.09 | G11: =CHOOSE($C$5,G8,G9,G10) -> 0.08 | H11: =CHOOSE($C$5,H8,H9,H10) -> 0.07 | I11: =CHOOSE($C$5,I8,I9,I10) -> 0.06
B13: Operating assumptions
B14: COGS (% of revenue) | E14: 0.6 | F14: 0.595 | G14: 0.59 | H14: 0.59 | I14: 0.59
B15: SG&A (% of revenue) | E15: 0.2 | F15: 0.2 | G15: 0.195 | H15: 0.195 | I15: 0.19
B16: D&A (% of revenue) | E16: 0.05 | F16: 0.05 | G16: 0.05 | H16: 0.05 | I16: 0.05
B17: Capex (% of revenue) | E17: 0.065 | F17: 0.06 | G17: 0.06 | H17: 0.055 | I17: 0.055
B18: Tax rate | E18: 0.25 | F18: 0.25 | G18: 0.25 | H18: 0.25 | I18: 0.25
B20: Working capital
B21: Receivable days (DSO) | E21: 50 | F21: 50 | G21: 50 | H21: 50 | I21: 50
B22: Inventory days (DIO, on COGS) | E22: 60 | F22: 60 | G22: 60 | H22: 60 | I22: 60
B23: Payable days (DPO, on COGS) | E23: 45 | F23: 45 | G23: 45 | H23: 45 | I23: 45
B25: Financing
B26: Interest rate (on opening debt) | E26: 0.07 | F26: 0.07 | G26: 0.07 | H26: 0.07 | I26: 0.07
B27: Debt repayment | E27: 300 | F27: 300 | G27: 300 | H27: 300 | I27: 300
B28: Dividend payout (% of net income) | E28: 0.3 | F28: 0.3 | G28: 0.3 | H28: 0.3 | I28: 0.3
B30: Notes: interest is charged on opening debt to avoid a circular reference. All inputs are illustrative.

Sheet Income Statement
B1: Income Statement
B2: Illustrative Manufacturing Co. ($ thousands)
C4: 2024A | D4: 2025A | E4: 2026E | F4: 2027E | G4: 2028E | H4: 2029E | I4: 2030E
B5: Revenue | C5: 10800 | D5: 12000 | E5: =D5*(1+Assumptions!E11) -> 13200 | F5: =E5*(1+Assumptions!F11) -> 14388 | G5: =F5*(1+Assumptions!G11) -> 15539.04 | H5: =G5*(1+Assumptions!H11) -> 16626.773 | I5: =H5*(1+Assumptions!I11) -> 17624.379
B6: Growth | D6: =D5/C5-1 -> 0.11111111 | E6: =E5/D5-1 -> 0.1 | F6: =F5/E5-1 -> 0.09 | G6: =G5/F5-1 -> 0.08 | H6: =H5/G5-1 -> 0.07 | I6: =I5/H5-1 -> 0.06
B7: Cost of goods sold | C7: -6588 | D7: -7200 | E7: =-E5*Assumptions!E14 -> -7920 | F7: =-F5*Assumptions!F14 -> -8560.86 | G7: =-G5*Assumptions!G14 -> -9168.0336 | H7: =-H5*Assumptions!H14 -> -9809.796 | I7: =-I5*Assumptions!I14 -> -10398.384
B8: Gross profit | C8: =C5+C7 -> 4212 | D8: =D5+D7 -> 4800 | E8: =E5+E7 -> 5280 | F8: =F5+F7 -> 5827.14 | G8: =G5+G7 -> 6371.0064 | H8: =H5+H7 -> 6816.9768 | I8: =I5+I7 -> 7225.9955
B9: Gross margin | C9: =IF(C5=0,0,C8/C5) -> 0.39 | D9: =IF(D5=0,0,D8/D5) -> 0.4 | E9: =IF(E5=0,0,E8/E5) -> 0.4 | F9: =IF(F5=0,0,F8/F5) -> 0.405 | G9: =IF(G5=0,0,G8/G5) -> 0.41 | H9: =IF(H5=0,0,H8/H5) -> 0.41 | I9: =IF(I5=0,0,I8/I5) -> 0.41
B10: SG&A | C10: -2268 | D10: -2460 | E10: =-E5*Assumptions!E15 -> -2640 | F10: =-F5*Assumptions!F15 -> -2877.6 | G10: =-G5*Assumptions!G15 -> -3030.1128 | H10: =-H5*Assumptions!H15 -> -3242.2207 | I10: =-I5*Assumptions!I15 -> -3348.632
B11: EBITDA | C11: =C8+C10 -> 1944 | D11: =D8+D10 -> 2340 | E11: =E8+E10 -> 2640 | F11: =F8+F10 -> 2949.54 | G11: =G8+G10 -> 3340.8936 | H11: =H8+H10 -> 3574.7562 | I11: =I8+I10 -> 3877.3634
B12: EBITDA margin | C12: =IF(C5=0,0,C11/C5) -> 0.18 | D12: =IF(D5=0,0,D11/D5) -> 0.195 | E12: =IF(E5=0,0,E11/E5) -> 0.2 | F12: =IF(F5=0,0,F11/F5) -> 0.205 | G12: =IF(G5=0,0,G11/G5) -> 0.215 | H12: =IF(H5=0,0,H11/H5) -> 0.215 | I12: =IF(I5=0,0,I11/I5) -> 0.22
B13: Depreciation & amortisation | C13: -540 | D13: -600 | E13: =-E5*Assumptions!E16 -> -660 | F13: =-F5*Assumptions!F16 -> -719.4 | G13: =-G5*Assumptions!G16 -> -776.952 | H13: =-H5*Assumptions!H16 -> -831.33864 | I13: =-I5*Assumptions!I16 -> -881.21896
B14: EBIT | C14: =C11+C13 -> 1404 | D14: =D11+D13 -> 1740 | E14: =E11+E13 -> 1980 | F14: =F11+F13 -> 2230.14 | G14: =G11+G13 -> 2563.9416 | H14: =H11+H13 -> 2743.4175 | I14: =I11+I13 -> 2996.1445
B15: Interest expense | C15: -215 | D15: -200 | E15: =-'Balance Sheet'!D17*Assumptions!E26 -> -210 | F15: =-'Balance Sheet'!E17*Assumptions!F26 -> -189 | G15: =-'Balance Sheet'!F17*Assumptions!G26 -> -168 | H15: =-'Balance Sheet'!G17*Assumptions!H26 -> -147 | I15: =-'Balance Sheet'!H17*Assumptions!I26 -> -126
B16: Profit before tax | C16: =C14+C15 -> 1189 | D16: =D14+D15 -> 1540 | E16: =E14+E15 -> 1770 | F16: =F14+F15 -> 2041.14 | G16: =G14+G15 -> 2395.9416 | H16: =H14+H15 -> 2596.4175 | I16: =I14+I15 -> 2870.1445
B17: Income tax | C17: =-MAX(0,C16*0.25) -> -297.25 | D17: =-MAX(0,D16*0.25) -> -385 | E17: =-MAX(0,E16*Assumptions!E18) -> -442.5 | F17: =-MAX(0,F16*Assumptions!F18) -> -510.285 | G17: =-MAX(0,G16*Assumptions!G18) -> -598.9854 | H17: =-MAX(0,H16*Assumptions!H18) -> -649.10438 | I17: =-MAX(0,I16*Assumptions!I18) -> -717.53611
B18: Net income | C18: =C16+C17 -> 891.75 | D18: =D16+D17 -> 1155 | E18: =E16+E17 -> 1327.5 | F18: =F16+F17 -> 1530.855 | G18: =G16+G17 -> 1796.9562 | H18: =H16+H17 -> 1947.3131 | I18: =I16+I17 -> 2152.6083
B19: Net margin | C19: =IF(C5=0,0,C18/C5) -> 0.082569444 | D19: =IF(D5=0,0,D18/D5) -> 0.09625 | E19: =IF(E5=0,0,E18/E5) -> 0.10056818 | F19: =IF(F5=0,0,F18/F5) -> 0.10639804 | G19: =IF(G5=0,0,G18/G5) -> 0.11564139 | H19: =IF(H5=0,0,H18/H5) -> 0.11711913 | I19: =IF(I5=0,0,I18/I5) -> 0.12213811

Sheet Balance Sheet
B1: Balance Sheet
B2: Illustrative Manufacturing Co. ($ thousands)
C4: 2024A | D4: 2025A | E4: 2026E | F4: 2027E | G4: 2028E | H4: 2029E | I4: 2030E
B5: Assets
B6: Cash | C6: 900 | D6: 908 | E6: ='Cash Flow'!E20 -> 1145.5514 | F6: ='Cash Flow'!F20 -> 1584.1934 | G6: ='Cash Flow'!G20 -> 2204.0433 | H6: ='Cash Flow'!H20 -> 3008.6504 | I6: ='Cash Flow'!I20 -> 3966.5074
B7: Accounts receivable | C7: 1450 | D7: 1644 | E7: ='Income Statement'!E5*Assumptions!E21/365 -> 1808.2192 | F7: ='Income Statement'!F5*Assumptions!F21/365 -> 1970.9589 | G7: ='Income Statement'!G5*Assumptions!G21/365 -> 2128.6356 | H7: ='Income Statement'!H5*Assumptions!H21/365 -> 2277.6401 | I7: ='Income Statement'!I5*Assumptions!I21/365 -> 2414.2985
B8: Inventory | C8: 1080 | D8: 1184 | E8: =-'Income Statement'!E7*Assumptions!E22/365 -> 1301.9178 | F8: =-'Income Statement'!F7*Assumptions!F22/365 -> 1407.2647 | G8: =-'Income Statement'!G7*Assumptions!G22/365 -> 1507.074 | H8: =-'Income Statement'!H7*Assumptions!H22/365 -> 1612.5692 | I8: =-'Income Statement'!I7*Assumptions!I22/365 -> 1709.3233
B9: Total current assets | C9: =SUM(C6:C8) -> 3430 | D9: =SUM(D6:D8) -> 3736 | E9: =SUM(E6:E8) -> 4255.6884 | F9: =SUM(F6:F8) -> 4962.417 | G9: =SUM(G6:G8) -> 5839.753 | H9: =SUM(H6:H8) -> 6898.8597 | I9: =SUM(I6:I8) -> 8090.1292
B10: Property, plant & equipment (net) | C10: 3700 | D10: 4000 | E10: =D10-'Cash Flow'!E13-'Cash Flow'!E7 -> 4198 | F10: =E10-'Cash Flow'!F13-'Cash Flow'!F7 -> 4341.88 | G10: =F10-'Cash Flow'!G13-'Cash Flow'!G7 -> 4497.2704 | H10: =G10-'Cash Flow'!H13-'Cash Flow'!H7 -> 4580.4043 | I10: =H10-'Cash Flow'!I13-'Cash Flow'!I7 -> 4668.5262
B11: Total assets | C11: =C9+C10 -> 7130 | D11: =D9+D10 -> 7736 | E11: =E9+E10 -> 8453.6884 | F11: =F9+F10 -> 9304.297 | G11: =G9+G10 -> 10337.023 | H11: =H9+H10 -> 11479.264 | I11: =I9+I10 -> 12758.655
B13: Liabilities & equity
B14: Accounts payable | C14: 790 | D14: 888 | E14: =-'Income Statement'!E7*Assumptions!E23/365 -> 976.43836 | F14: =-'Income Statement'!F7*Assumptions!F23/365 -> 1055.4485 | G14: =-'Income Statement'!G7*Assumptions!G23/365 -> 1130.3055 | H14: =-'Income Statement'!H7*Assumptions!H23/365 -> 1209.4269 | I14: =-'Income Statement'!I7*Assumptions!I23/365 -> 1281.9925
B15: Total current liabilities | C15: =C14 -> 790 | D15: =D14 -> 888 | E15: =E14 -> 976.43836 | F15: =F14 -> 1055.4485 | G15: =G14 -> 1130.3055 | H15: =H14 -> 1209.4269 | I15: =I14 -> 1281.9925
B17: Long-term debt | C17: 3300 | D17: 3000 | E17: =MAX(0,D17-Assumptions!E27) -> 2700 | F17: =MAX(0,E17-Assumptions!F27) -> 2400 | G17: =MAX(0,F17-Assumptions!G27) -> 2100 | H17: =MAX(0,G17-Assumptions!H27) -> 1800 | I17: =MAX(0,H17-Assumptions!I27) -> 1500
B18: Total liabilities | C18: =C15+C17 -> 4090 | D18: =D15+D17 -> 3888 | E18: =E15+E17 -> 3676.4384 | F18: =F15+F17 -> 3455.4485 | G18: =G15+G17 -> 3230.3055 | H18: =H15+H17 -> 3009.4269 | I18: =I15+I17 -> 2781.9925
B20: Common stock | C20: 1000 | D20: 1000 | E20: =D20 -> 1000 | F20: =E20 -> 1000 | G20: =F20 -> 1000 | H20: =G20 -> 1000 | I20: =H20 -> 1000
B21: Retained earnings | C21: 2040 | D21: 2848 | E21: =D21+'Income Statement'!E18+'Cash Flow'!E17 -> 3777.25 | F21: =E21+'Income Statement'!F18+'Cash Flow'!F17 -> 4848.8485 | G21: =F21+'Income Statement'!G18+'Cash Flow'!G17 -> 6106.7178 | H21: =G21+'Income Statement'!H18+'Cash Flow'!H17 -> 7469.837 | I21: =H21+'Income Statement'!I18+'Cash Flow'!I17 -> 8976.6629
B22: Total equity | C22: =C20+C21 -> 3040 | D22: =D20+D21 -> 3848 | E22: =E20+E21 -> 4777.25 | F22: =F20+F21 -> 5848.8485 | G22: =G20+G21 -> 7106.7178 | H22: =H20+H21 -> 8469.837 | I22: =I20+I21 -> 9976.6629
B23: Total liabilities & equity | C23: =C18+C22 -> 7130 | D23: =D18+D22 -> 7736 | E23: =E18+E22 -> 8453.6884 | F23: =F18+F22 -> 9304.297 | G23: =G18+G22 -> 10337.023 | H23: =H18+H22 -> 11479.264 | I23: =I18+I22 -> 12758.655

Sheet Cash Flow
B1: Cash Flow Statement
B2: Illustrative Manufacturing Co. ($ thousands)
C4: 2024A | D4: 2025A | E4: 2026E | F4: 2027E | G4: 2028E | H4: 2029E | I4: 2030E
B5: Operating activities
B6: Net income | E6: ='Income Statement'!E18 -> 1327.5 | F6: ='Income Statement'!F18 -> 1530.855 | G6: ='Income Statement'!G18 -> 1796.9562 | H6: ='Income Statement'!H18 -> 1947.3131 | I6: ='Income Statement'!I18 -> 2152.6083
B7: Depreciation & amortisation | E7: =-'Income Statement'!E13 -> 660 | F7: =-'Income Statement'!F13 -> 719.4 | G7: =-'Income Statement'!G13 -> 776.952 | H7: =-'Income Statement'!H13 -> 831.33864 | I7: =-'Income Statement'!I13 -> 881.21896
B8: (Increase) / decrease in receivables | E8: ='Balance Sheet'!D7-'Balance Sheet'!E7 -> -164.21918 | F8: ='Balance Sheet'!E7-'Balance Sheet'!F7 -> -162.73973 | G8: ='Balance Sheet'!F7-'Balance Sheet'!G7 -> -157.67671 | H8: ='Balance Sheet'!G7-'Balance Sheet'!H7 -> -149.00449 | I8: ='Balance Sheet'!H7-'Balance Sheet'!I7 -> -136.65841
B9: (Increase) / decrease in inventory | E9: ='Balance Sheet'!D8-'Balance Sheet'!E8 -> -117.91781 | F9: ='Balance Sheet'!E8-'Balance Sheet'!F8 -> -105.34685 | G9: ='Balance Sheet'!F8-'Balance Sheet'!G8 -> -99.809359 | H9: ='Balance Sheet'!G8-'Balance Sheet'!H8 -> -105.49518 | I9: ='Balance Sheet'!H8-'Balance Sheet'!I8 -> -96.754152
B10: Increase / (decrease) in payables | E10: ='Balance Sheet'!E14-'Balance Sheet'!D14 -> 88.438356 | F10: ='Balance Sheet'!F14-'Balance Sheet'!E14 -> 79.010137 | G10: ='Balance Sheet'!G14-'Balance Sheet'!F14 -> 74.857019 | H10: ='Balance Sheet'!H14-'Balance Sheet'!G14 -> 79.121386 | I10: ='Balance Sheet'!I14-'Balance Sheet'!H14 -> 72.565614
B11: Cash from operating activities | E11: =SUM(E6:E10) -> 1793.8014 | F11: =SUM(F6:F10) -> 2061.1786 | G11: =SUM(G6:G10) -> 2391.2791 | H11: =SUM(H6:H10) -> 2603.2735 | I11: =SUM(I6:I10) -> 2872.9804
B12: Investing activities
B13: Capital expenditure | E13: =-'Income Statement'!E5*Assumptions!E17 -> -858 | F13: =-'Income Statement'!F5*Assumptions!F17 -> -863.28 | G13: =-'Income Statement'!G5*Assumptions!G17 -> -932.3424 | H13: =-'Income Statement'!H5*Assumptions!H17 -> -914.4725 | I13: =-'Income Statement'!I5*Assumptions!I17 -> -969.34085
B14: Cash from investing activities | E14: =E13 -> -858 | F14: =F13 -> -863.28 | G14: =G13 -> -932.3424 | H14: =H13 -> -914.4725 | I14: =I13 -> -969.34085
B15: Financing activities
B16: Debt repayment | E16: ='Balance Sheet'!E17-'Balance Sheet'!D17 -> -300 | F16: ='Balance Sheet'!F17-'Balance Sheet'!E17 -> -300 | G16: ='Balance Sheet'!G17-'Balance Sheet'!F17 -> -300 | H16: ='Balance Sheet'!H17-'Balance Sheet'!G17 -> -300 | I16: ='Balance Sheet'!I17-'Balance Sheet'!H17 -> -300
B17: Dividends paid | E17: =-MAX(0,'Income Statement'!E18*Assumptions!E28) -> -398.25 | F17: =-MAX(0,'Income Statement'!F18*Assumptions!F28) -> -459.2565 | G17: =-MAX(0,'Income Statement'!G18*Assumptions!G28) -> -539.08686 | H17: =-MAX(0,'Income Statement'!H18*Assumptions!H28) -> -584.19394 | I17: =-MAX(0,'Income Statement'!I18*Assumptions!I28) -> -645.7825
B18: Cash from financing activities | E18: =E16+E17 -> -698.25 | F18: =F16+F17 -> -759.2565 | G18: =G16+G17 -> -839.08686 | H18: =H16+H17 -> -884.19394 | I18: =I16+I17 -> -945.7825
B19: Net change in cash | E19: =E11+E14+E18 -> 237.55137 | F19: =F11+F14+F18 -> 438.64206 | G19: =G11+G14+G18 -> 619.84989 | H19: =H11+H14+H18 -> 804.60704 | I19: =I11+I14+I18 -> 957.857
B20: Ending cash | E20: ='Balance Sheet'!D6+E19 -> 1145.5514 | F20: ='Balance Sheet'!E6+F19 -> 1584.1934 | G20: ='Balance Sheet'!F6+G19 -> 2204.0433 | H20: ='Balance Sheet'!G6+H19 -> 3008.6504 | I20: ='Balance Sheet'!H6+I19 -> 3966.5074

Sheet Checks
B1: Model Checks
B2: Illustrative Manufacturing Co. (difference should be zero)
C4: 2024A | D4: 2025A | E4: 2026E | F4: 2027E | G4: 2028E | H4: 2029E | I4: 2030E
B5: Balance sheet: assets less liabilities & equity | C5: =ROUND('Balance Sheet'!C11-'Balance Sheet'!C23,2) -> 0 | D5: =ROUND('Balance Sheet'!D11-'Balance Sheet'!D23,2) -> 0 | E5: =ROUND('Balance Sheet'!E11-'Balance Sheet'!E23,2) -> 0 | F5: =ROUND('Balance Sheet'!F11-'Balance Sheet'!F23,2) -> 0 | G5: =ROUND('Balance Sheet'!G11-'Balance Sheet'!G23,2) -> 0 | H5: =ROUND('Balance Sheet'!H11-'Balance Sheet'!H23,2) -> 0 | I5: =ROUND('Balance Sheet'!I11-'Balance Sheet'!I23,2) -> 0
B6: Cash: balance sheet less cash flow ending cash | E6: =ROUND('Balance Sheet'!E6-'Cash Flow'!E20,2) -> 0 | F6: =ROUND('Balance Sheet'!F6-'Cash Flow'!F20,2) -> 0 | G6: =ROUND('Balance Sheet'!G6-'Cash Flow'!G20,2) -> 0 | H6: =ROUND('Balance Sheet'!H6-'Cash Flow'!H20,2) -> 0 | I6: =ROUND('Balance Sheet'!I6-'Cash Flow'!I20,2) -> 0
B8: All checks pass? | C8: =IF(SUMPRODUCT(ABS(C5:I6))=0,"OK","ERROR") -> OK
